<annotations><filename>image6.png</filename><folder>/home/gina/gastro_dataset/img/labels</folder><size><width>640</width><height>480</height><depth>3</depth></size><object><name>panhandle</name><pose>Unspecified</pose><truncated>0</truncated><difficult>0</difficult><bndbox><xmin>53.500159999999994</xmin><ymin>1.9999199999999995</ymin><xmax>132.0</xmax><ymax>58.00008</ymax></bndbox></object><object><name>stovetop</name><pose>Unspecified</pose><truncated>0</truncated><difficult>0</difficult><bndbox><xmin>186.0</xmin><ymin>8.666879999999992</ymin><xmax>470.0</xmax><ymax>270.0</ymax></bndbox></object><object><name>pan</name><pose>Unspecified</pose><truncated>0</truncated><difficult>0</difficult><bndbox><xmin>87.50016000000002</xmin><ymin>68.66664</ymin><xmax>478.0</xmax><ymax>316.66679999999997</ymax></bndbox></object><object><name>pasta</name><pose>Unspecified</pose><truncated>0</truncated><difficult>0</difficult><bndbox><xmin>161.49983999999998</xmin><ymin>139.33344</ymin><xmax>293.99968</xmax><ymax>284.66688</ymax></bndbox></object><object><name>panhandle</name><pose>Unspecified</pose><truncated>0</truncated><difficult>0</difficult><bndbox><xmin>314.0</xmin><ymin>91.3332</ymin><xmax>478.0</xmax><ymax>174.66648</ymax></bndbox></object></annotations>