<annotations><filename>image32.png</filename><folder>/home/gina/img/labels</folder><size><width>640</width><height>480</height><depth>3</depth></size><object><name>robot</name><pose>Unspecified</pose><truncated>0</truncated><difficult>0</difficult><bndbox><xmin>-0.000319999999988</xmin><ymin>59.33352</ymin><xmax>261.0</xmax><ymax>456.00024</ymax></bndbox></object><object><name>pan</name><pose>Unspecified</pose><truncated>0</truncated><difficult>0</difficult><bndbox><xmin>409.0</xmin><ymin>294.66648</ymin><xmax>627.99968</xmax><ymax>479.99976</ymax></bndbox></object><object><name>pasta</name><pose>Unspecified</pose><truncated>0</truncated><difficult>0</difficult><bndbox><xmin>435.49984</xmin><ymin>380.00016</ymin><xmax>563.99968</xmax><ymax>461.33328</ymax></bndbox></object><object><name>sauce dispenser</name><pose>Unspecified</pose><truncated>0</truncated><difficult>0</difficult><bndbox><xmin>303.50016</xmin><ymin>81.33336</ymin><xmax>417.00032</xmax><ymax>305.33352</ymax></bndbox></object><object><name>sauce dispenser</name><pose>Unspecified</pose><truncated>0</truncated><difficult>0</difficult><bndbox><xmin>415.49984</xmin><ymin>6.66672</ymin><xmax>516.50016</xmax><ymax>305.33328</ymax></bndbox></object><object><name>sauce dispenser</name><pose>Unspecified</pose><truncated>0</truncated><difficult>0</difficult><bndbox><xmin>521.0</xmin><ymin>43.99992</ymin><xmax>639.0</xmax><ymax>337.3332</ymax></bndbox></object><object><name>stovetop</name><pose>Unspecified</pose><truncated>0</truncated><difficult>0</difficult><bndbox><xmin>369.0</xmin><ymin>390.0</ymin><xmax>626.00032</xmax><ymax>480.0</ymax></bndbox></object><object><name>panhandle</name><pose>Unspecified</pose><truncated>0</truncated><difficult>0</difficult><bndbox><xmin>312.00032</xmin><ymin>403.99992</ymin><xmax>372.50016</xmax><ymax>479.99976</ymax></bndbox></object><object><name>panhandle</name><pose>Unspecified</pose><truncated>0</truncated><difficult>0</difficult><bndbox><xmin>549.99968</xmin><ymin>301.3332</ymin><xmax>621.49984</xmax><ymax>367.99992</ymax></bndbox></object></annotations>