<annotations><filename>image149.png</filename><folder>/home/gina/Yolo_mark/x64/Release/data/img/</folder><size><width>640</width><height>480</height><depth>3</depth></size><object><name>pasta dispenser</name><pose>Unspecified</pose><truncated>0</truncated><difficult>0</difficult><bndbox><xmin>178.99967999999998</xmin><ymin>19.999920000000003</ymin><xmax>432.49983999999995</xmax><ymax>479.99976000000004</ymax></bndbox></object><object><name>pasta dispenser</name><pose>Unspecified</pose><truncated>0</truncated><difficult>0</difficult><bndbox><xmin>397.0</xmin><ymin>47.33328</ymin><xmax>517.49984</xmax><ymax>417.99984</ymax></bndbox></object><object><name>pasta dispenser</name><pose>Unspecified</pose><truncated>0</truncated><difficult>0</difficult><bndbox><xmin>503.00000000000006</xmin><ymin>63.33359999999999</ymin><xmax>572.0003200000001</xmax><ymax>392.00016</ymax></bndbox></object><object><name>pasta</name><pose>Unspecified</pose><truncated>0</truncated><difficult>0</difficult><bndbox><xmin>515.99968</xmin><ymin>273.3336</ymin><xmax>565.0000000000001</xmax><ymax>332.00016</ymax></bndbox></object><object><name>pasta</name><pose>Unspecified</pose><truncated>0</truncated><difficult>0</difficult><bndbox><xmin>379.49984000000006</xmin><ymin>316.66655999999995</ymin><xmax>499.0</xmax><ymax>409.99967999999996</ymax></bndbox></object><object><name>pasta</name><pose>Unspecified</pose><truncated>0</truncated><difficult>0</difficult><bndbox><xmin>254.00031999999996</xmin><ymin>379.99992000000003</ymin><xmax>422.50015999999994</xmax><ymax>479.99976</ymax></bndbox></object></annotations>