<annotations><filename>IMG_1133.jpg</filename><folder>/home/inst/Downloads/Yolo_mark-master/x64/Release/data/img/labels</folder><size><width>4032</width><height>3024</height><depth>3</depth></size><object><name>pan</name><pose>Unspecified</pose><truncated>0</truncated><difficult>0</difficult><bndbox><xmin>475.648992</xmin><ymin>1268.398656</ymin><xmax>2756.248992</xmax><ymax>2032.799328</ymax></bndbox></object><object><name>pan</name><pose>Unspecified</pose><truncated>0</truncated><difficult>0</difficult><bndbox><xmin>3080.697984</xmin><ymin>1201.199328</ymin><xmax>4032.0</xmax><ymax>2024.398656</ymax></bndbox></object><object><name>panhandle</name><pose>Unspecified</pose><truncated>0</truncated><difficult>0</difficult><bndbox><xmin>469.351008</xmin><ymin>1747.19916</ymin><xmax>1363.951008</xmax><ymax>1948.800168</ymax></bndbox></object></annotations>